<?xml version="1.0" encoding="UTF-8" standalone="yes"?>
<AssignMessage async="false" continueOnError="false" enabled="true" name="AM-GetLoan">
    <DisplayName>AM-GetLoan</DisplayName>
    <FaultRules/>
    <Properties/>
    <Set>
        <Headers>
            <Header name="Authorization">{private.Authorization.loans.service}</Header>
        </Headers>
        <Verb>GET</Verb>
        <Path>/personal-credit/contracts/active/{payload.person_id}</Path>
    </Set>
    <IgnoreUnresolvedVariables>true</IgnoreUnresolvedVariables>
    <AssignTo type="request" transport="http" createNew="true">request</AssignTo>
</AssignMessage>
