{
  "accessType": "",
  "apiProducts": [],
  "appFamily": "default",
  "appId": "1a1fcf79-e3e1-4671-8ba2-ac4f1c3c2d3f",
  "attributes": [
    {
      "name": "ADMIN_EMAIL",
      "value": "ashwinknaik@google.com"
    },
    {
      "name": "DisplayName",
      "value": "My App 1725297901"
    }
  ],
  "callbackUrl": "example.com",
  "createdAt": 1725297901805,
  "createdBy": "opdk@google.com",
  "credentials": [
    {
      "apiProducts": [
        {
          "apiproduct": "OAuth",
          "status": "approved"
        }
      ],
      "attributes": [],
      "consumerKey": "3hTvLOe6maJrGtdEq3TtXAbnes2yHDKm",
      "consumerSecret": "y3Xa7qbjRNqBLZgZ",
      "expiresAt": -1,
      "issuedAt": 1725297901823,
      "scopes": [],
      "status": "approved"
    }
  ],
  "credentialsLoaded": true,
  "developerId": "yAPY8uvd9ero03U6",
  "lastModifiedAt": 1725297901805,
  "lastModifiedBy": "opdk@google.com",
  "name": "app-1725297901",
  "scopes": [],
  "status": "approved"
}