{
  "accessType": "",
  "apiProducts": [],
  "appFamily": "default",
  "appId": "5eab37ac-083c-4f5c-a825-2fbf5bbce8f3",
  "attributes": [
    {
      "name": "ADMIN_EMAIL",
      "value": "ashwinknaik@google.com"
    },
    {
      "name": "DisplayName",
      "value": "My App 1725297616"
    }
  ],
  "callbackUrl": "example.com",
  "createdAt": 1725297616900,
  "createdBy": "opdk@google.com",
  "credentials": [
    {
      "apiProducts": [
        {
          "apiproduct": "OAuth",
          "status": "approved"
        }
      ],
      "attributes": [],
      "consumerKey": "7guGWPGqS3tSRBzzO2QhiAImGMNLPGFk",
      "consumerSecret": "cSvWd4UnHMdJfxAT",
      "expiresAt": -1,
      "issuedAt": 1725297616913,
      "scopes": [],
      "status": "approved"
    }
  ],
  "credentialsLoaded": true,
  "developerId": "yAPY8uvd9ero03U6",
  "lastModifiedAt": 1725297616900,
  "lastModifiedBy": "opdk@google.com",
  "name": "app-1725297616",
  "scopes": [],
  "status": "approved"
}