{
  "accessType": "",
  "apiProducts": [],
  "appFamily": "default",
  "appId": "6dbae33d-9b83-4b97-8d41-dc4f3fa221a2",
  "attributes": [
    {
      "name": "ADMIN_EMAIL",
      "value": "ashwinknaik@google.com"
    },
    {
      "name": "DisplayName",
      "value": "My App 1725297911"
    }
  ],
  "callbackUrl": "example.com",
  "createdAt": 1725297911423,
  "createdBy": "opdk@google.com",
  "credentials": [
    {
      "apiProducts": [
        {
          "apiproduct": "OAuth",
          "status": "approved"
        }
      ],
      "attributes": [],
      "consumerKey": "9Mlo5ZOmexKp6CsP2mmciC7T6rmnGrXs",
      "consumerSecret": "EHvfdSHFyA51PAur",
      "expiresAt": -1,
      "issuedAt": 1725297911441,
      "scopes": [],
      "status": "approved"
    }
  ],
  "credentialsLoaded": true,
  "developerId": "yAPY8uvd9ero03U6",
  "lastModifiedAt": 1725297911423,
  "lastModifiedBy": "opdk@google.com",
  "name": "app-1725297911",
  "scopes": [],
  "status": "approved"
}