{
  "accessType": "",
  "apiProducts": [],
  "appFamily": "default",
  "appId": "8521ea80-91fe-499b-9908-33c3a5746ccf",
  "attributes": [
    {
      "name": "ADMIN_EMAIL",
      "value": "ashwinknaik@google.com"
    },
    {
      "name": "DisplayName",
      "value": "My App 1725297937"
    }
  ],
  "callbackUrl": "example.com",
  "createdAt": 1725297937983,
  "createdBy": "opdk@google.com",
  "credentials": [
    {
      "apiProducts": [
        {
          "apiproduct": "OAuth",
          "status": "approved"
        }
      ],
      "attributes": [],
      "consumerKey": "sCOsGxU35alw1kKAhHEMJ3j8ETlkKjAy",
      "consumerSecret": "ut8GA9Gd7F4FmxgA",
      "expiresAt": -1,
      "issuedAt": 1725297938001,
      "scopes": [],
      "status": "approved"
    }
  ],
  "credentialsLoaded": true,
  "developerId": "yAPY8uvd9ero03U6",
  "lastModifiedAt": 1725297937983,
  "lastModifiedBy": "opdk@google.com",
  "name": "app-1725297937",
  "scopes": [],
  "status": "approved"
}