{
  "accessType": "",
  "apiProducts": [],
  "appFamily": "default",
  "appId": "b4b20395-41c8-47cc-bf26-58e2069ce85a",
  "attributes": [
    {
      "name": "ADMIN_EMAIL",
      "value": "ashwinknaik@google.com"
    },
    {
      "name": "DisplayName",
      "value": "My App 1725297313"
    }
  ],
  "callbackUrl": "example.com",
  "createdAt": 1725297314033,
  "createdBy": "opdk@google.com",
  "credentials": [
    {
      "apiProducts": [
        {
          "apiproduct": "OAuth",
          "status": "approved"
        }
      ],
      "attributes": [],
      "consumerKey": "dI9fARZrSThg5GSTA0oFAn0AGK8FVXEA",
      "consumerSecret": "2a9yOVwASRmnoICA",
      "expiresAt": -1,
      "issuedAt": 1725297314040,
      "scopes": [],
      "status": "approved"
    }
  ],
  "credentialsLoaded": true,
  "developerId": "yAPY8uvd9ero03U6",
  "lastModifiedAt": 1725297314033,
  "lastModifiedBy": "opdk@google.com",
  "name": "app-1725297313",
  "scopes": [],
  "status": "approved"
}