{
  "accessType": "",
  "apiProducts": [],
  "appFamily": "default",
  "appId": "bdffa96a-1f68-47b8-b000-017a0a5586c8",
  "attributes": [
    {
      "name": "ADMIN_EMAIL",
      "value": "ashwinknaik@google.com"
    },
    {
      "name": "DisplayName",
      "value": "My App 1725297671"
    }
  ],
  "callbackUrl": "example.com",
  "createdAt": 1725297672029,
  "createdBy": "opdk@google.com",
  "credentials": [
    {
      "apiProducts": [
        {
          "apiproduct": "OAuth",
          "status": "approved"
        }
      ],
      "attributes": [],
      "consumerKey": "5a5fW9itlzxyuIiBdG9ivKdcypXBHsJv",
      "consumerSecret": "bYER8rfFGkS5jvyy",
      "expiresAt": -1,
      "issuedAt": 1725297672042,
      "scopes": [],
      "status": "approved"
    }
  ],
  "credentialsLoaded": true,
  "developerId": "yAPY8uvd9ero03U6",
  "lastModifiedAt": 1725297672029,
  "lastModifiedBy": "opdk@google.com",
  "name": "app-1725297671",
  "scopes": [],
  "status": "approved"
}