{
  "apiResources": [
    "/"
  ],
  "approvalType": "auto",
  "attributes": [
    {
      "name": "access",
      "value": "public"
    }
  ],
  "createdAt": 1725347331666,
  "createdBy": "opdk@google.com",
  "description": "My API product 1725347331",
  "displayName": "My API product 1725347331",
  "environments": [
    "test"
  ],
  "lastModifiedAt": 1725347331666,
  "lastModifiedBy": "opdk@google.com",
  "name": "api-product-1725347331",
  "proxies": [
    "google",
    "git"
  ],
  "scopes": []
}